friendlytagloader/__init__.py
friendlytagloader/models.py
friendlytagloader/templatetags/__init__.py
friendlytagloader/templatetags/friendly_loader.py
django_friendly_tag_loader-1.3.2.dist-info/LICENSE
django_friendly_tag_loader-1.3.2.dist-info/METADATA
django_friendly_tag_loader-1.3.2.dist-info/WHEEL
django_friendly_tag_loader-1.3.2.dist-info/top_level.txt
django_friendly_tag_loader-1.3.2.dist-info/RECORD
