Metadata-Version: 2.1
Name: django-friendly-tag-loader
Version: 1.3.2
Summary: Want to optionally use a template tag library? Use this!
Author-email: Jaap Roes <jaap.roes@gmail.com>, Adam Taylor <ataylor32@gmail.com>
License: MIT
Project-URL: Homepage, https://github.com/ataylor32/django-friendly-tag-loader
Project-URL: Repository, https://github.com/ataylor32/django-friendly-tag-loader.git
Project-URL: Issues, https://github.com/ataylor32/django-friendly-tag-loader/issues
Project-URL: Changelog, https://github.com/ataylor32/django-friendly-tag-loader/blob/master/CHANGES.rst
Classifier: Development Status :: 5 - Production/Stable
Classifier: Environment :: Web Environment
Classifier: Framework :: Django
Classifier: Intended Audience :: Developers
Classifier: License :: OSI Approved :: MIT License
Classifier: Operating System :: OS Independent
Classifier: Programming Language :: Python :: 2
Classifier: Programming Language :: Python :: 2.7
Classifier: Programming Language :: Python :: 3
Classifier: Programming Language :: Python :: 3.4
Classifier: Programming Language :: Python :: 3.5
Classifier: Programming Language :: Python :: 3.6
Classifier: Programming Language :: Python :: 3.7
Classifier: Programming Language :: Python :: 3.8
Classifier: Programming Language :: Python :: 3.9
Classifier: Programming Language :: Python :: 3.10
Classifier: Programming Language :: Python :: 3.11
Classifier: Programming Language :: Python :: 3.12
License-File: LICENSE
